adapta/__init__.py
adapta/_version.py
adapta/connectors/__init__.py
adapta/connectors/service_bus/__init__.py
adapta/connectors/service_bus/_connector.py
adapta/logs/README.md
adapta/logs/__init__.py
adapta/logs/_async_logger.py
adapta/logs/_base.py
adapta/logs/_internal.py
adapta/logs/_internal_logger.py
adapta/logs/_logger_interface.py
adapta/logs/handlers/__init__.py
adapta/logs/handlers/datadog_api_handler.py
adapta/logs/handlers/safe_stream_handler.py
adapta/logs/models/__init__.py
adapta/logs/models/_log_level.py
adapta/logs/models/_logs_metadata.py
adapta/metrics/__init__.py
adapta/metrics/_base.py
adapta/metrics/providers/README.md
adapta/metrics/providers/__init__.py
adapta/metrics/providers/datadog_provider.py
adapta/metrics/providers/void_provider.py
adapta/ml/__init__.py
adapta/ml/_model.py
adapta/ml/mlflow/__init__.py
adapta/ml/mlflow/_client.py
adapta/ml/mlflow/_functions.py
adapta/process_communication/__init__.py
adapta/process_communication/_models.py
adapta/schema_management/README.md
adapta/schema_management/__init__.py
adapta/schema_management/schema_entity.py
adapta/security/__init__.py
adapta/security/clients/README.md
adapta/security/clients/__init__.py
adapta/security/clients/_azure_client.py
adapta/security/clients/_base.py
adapta/security/clients/_local_client.py
adapta/security/clients/aws/__init__.py
adapta/security/clients/aws/_aws_client.py
adapta/security/clients/aws/_aws_credentials.py
adapta/security/clients/hashicorp_vault/__init__.py
adapta/security/clients/hashicorp_vault/hashicorp_vault_client.py
adapta/security/clients/hashicorp_vault/kubernetes_client.py
adapta/security/clients/hashicorp_vault/oidc_client.py
adapta/security/clients/hashicorp_vault/token_client.py
adapta/storage/__init__.py
adapta/storage/blob/README.md
adapta/storage/blob/__init__.py
adapta/storage/blob/azure_storage_client.py
adapta/storage/blob/base.py
adapta/storage/blob/local_storage_client.py
adapta/storage/blob/s3_storage_client.py
adapta-3.5.15.dist-info/METADATA
adapta-3.5.15.dist-info/WHEEL
adapta-3.5.15.dist-info/licenses/LICENSE
adapta-3.5.15.dist-info/RECORD
